{
  "NAME": "GW392",
  "PKG_TYPE": "QUAD",
  "HEIGHT": 98,
  "PIN_DATA": [
    {
      "INDEX": "1",
      "NAME": "IOL2A",
      "TYPE": "I/O",
      "BANK": 8,
      "DIFF": "P",
      "PAIR": "IOL2B",
      "DQS": "DQ0",
      "TRUELVDS": true
    },
    {
      "INDEX": "2",
      "NAME": "IOL2B",
      "TYPE": "I/O",
      "BANK": 8,
      "DIFF": "N",
      "PAIR": "IOL2A",
      "DQS": "DQ0",
      "TRUELVDS": true
    },
    {
      "INDEX": "3",
      "NAME": "IOL3A",
      "TYPE": "I/O",
      "BANK": 8,
      "DIFF": "P",
      "PAIR": "IOL3B",
      "DQS": "DQ0"
    },
    {
      "INDEX": "4",
      "NAME": "IOL3B",
      "TYPE": "I/O",
      "BANK": 8,
      "DIFF": "N",
      "PAIR": "IOL3A",
      "DQS": "DQ0"
    },
    {
      "INDEX": "5",
      "NAME": "IOL4A",
      "TYPE": "I/O",
      "BANK": 8,
      "CFG": "LPLL_T_FB",
      "DIFF": "P",
      "PAIR": "IOL4B",
      "DQS": "DQ0",
      "TRUELVDS": true
    },
    {
      "INDEX": "6",
      "NAME": "IOL4B",
      "TYPE": "I/O",
      "BANK": 8,
      "CFG": "LPLL_C_FB",
      "DIFF": "N",
      "PAIR": "IOL4A",
      "DQS": "DQ0",
      "TRUELVDS": true
    },
    {
      "INDEX": "7",
      "NAME": "IOL5A",
      "TYPE": "I/O",
      "BANK": 8,
      "CFG": "LPLL_T_IN",
      "DIFF": "P",
      "PAIR": "IOL5B",
      "DQS": "DQ0"
    },
    {
      "INDEX": "8",
      "NAME": "IOL5B",
      "TYPE": "I/O",
      "BANK": 8,
      "CFG": "LPLL_C_IN",
      "DIFF": "N",
      "PAIR": "IOL5A",
      "DQS": "DQ0"
    },
    {
      "INDEX": "9",
      "NAME": "IOL6A",
      "TYPE": "I/O",
      "BANK": 8,
      "DIFF": "P",
      "PAIR": "IOL6B",
      "DQS": "DQS0",
      "TRUELVDS": true
    },
    {
      "INDEX": "10",
      "NAME": "IOL6B",
      "TYPE": "I/O",
      "BANK": 8,
      "DIFF": "N",
      "PAIR": "IOL6A",
      "DQS": "DQS0",
      "TRUELVDS": true
    },
    {
      "INDEX": "11",
      "NAME": "IOL7A",
      "TYPE": "I/O",
      "BANK": 8,
      "DIFF": "P",
      "PAIR": "IOL7B",
      "DQS": "DQ0"
    },
    {
      "INDEX": "12",
      "NAME": "IOL7B",
      "TYPE": "I/O",
      "BANK": 8,
      "DIFF": "N",
      "PAIR": "IOL7A",
      "DQS": "DQ0"
    },
    {
      "INDEX": "13",
      "NAME": "IOL8A",
      "TYPE": "I/O",
      "BANK": 8,
      "DIFF": "P",
      "PAIR": "IOL8B",
      "DQS": "DQ0",
      "TRUELVDS": true
    },
    {
      "INDEX": "14",
      "NAME": "IOL8B",
      "TYPE": "I/O",
      "BANK": 8,
      "DIFF": "N",
      "PAIR": "IOL8A",
      "DQS": "DQ0",
      "TRUELVDS": true
    },
    {
      "INDEX": "15",
      "NAME": "IOL9A",
      "TYPE": "I/O",
      "BANK": 8,
      "DIFF": "P",
      "PAIR": "IOL9B",
      "DQS": "DQ0"
    },
    {
      "INDEX": "16",
      "NAME": "IOL9B",
      "TYPE": "I/O",
      "BANK": 8,
      "DIFF": "N",
      "PAIR": "IOL9A",
      "DQS": "DQ0"
    },
    {
      "INDEX": "17",
      "NAME": "IOL11A",
      "TYPE": "I/O",
      "BANK": 8,
      "DIFF": "P",
      "PAIR": "IOL11B",
      "DQS": "NONE",
      "TRUELVDS": true
    },
    {
      "INDEX": "18",
      "NAME": "IOL11B",
      "TYPE": "I/O",
      "BANK": 8,
      "DIFF": "N",
      "PAIR": "IOL11A",
      "DQS": "NONE",
      "TRUELVDS": true
    },
    {
      "INDEX": "19",
      "NAME": "IOL12A",
      "TYPE": "I/O",
      "BANK": 8,
      "DIFF": "P",
      "PAIR": "IOL12B",
      "DQS": "NONE"
    },
    {
      "INDEX": "20",
      "NAME": "IOL12B",
      "TYPE": "I/O",
      "BANK": 8,
      "DIFF": "N",
      "PAIR": "IOL12A",
      "DQS": "NONE"
    },
    {
      "INDEX": "21",
      "NAME": "IOL13A",
      "TYPE": "I/O",
      "BANK": 8,
      "DIFF": "P",
      "PAIR": "IOL13B",
      "DQS": "NONE",
      "TRUELVDS": true
    },
    {
      "INDEX": "22",
      "NAME": "IOL13B",
      "TYPE": "I/O",
      "BANK": 8,
      "DIFF": "N",
      "PAIR": "IOL13A",
      "DQS": "NONE",
      "TRUELVDS": true
    },
    {
      "INDEX": "23",
      "NAME": "IOL14A",
      "TYPE": "I/O",
      "BANK": 8,
      "CFG": "GCLKT_8",
      "DIFF": "P",
      "PAIR": "IOL14B",
      "DQS": "NONE"
    },
    {
      "INDEX": "24",
      "NAME": "IOL14B",
      "TYPE": "I/O",
      "BANK": 8,
      "CFG": "GCLKC_8",
      "DIFF": "N",
      "PAIR": "IOL14A",
      "DQS": "NONE"
    },
    {
      "INDEX": "25",
      "NAME": "IOL15A",
      "TYPE": "I/O",
      "BANK": 8,
      "DIFF": "P",
      "PAIR": "IOL15B",
      "DQS": "NONE",
      "TRUELVDS": true
    },
    {
      "INDEX": "26",
      "NAME": "IOL15B",
      "TYPE": "I/O",
      "BANK": 8,
      "DIFF": "N",
      "PAIR": "IOL15A",
      "DQS": "NONE",
      "TRUELVDS": true
    },
    {
      "INDEX": "27",
      "NAME": "IOL16A",
      "TYPE": "I/O",
      "BANK": 8,
      "DIFF": "P",
      "PAIR": "IOL16B",
      "DQS": "NONE"
    },
    {
      "INDEX": "28",
      "NAME": "IOL16B",
      "TYPE": "I/O",
      "BANK": 8,
      "DIFF": "N",
      "PAIR": "IOL16A",
      "DQS": "NONE"
    },
    {
      "INDEX": "29",
      "NAME": "IOL17A",
      "TYPE": "I/O",
      "BANK": 8,
      "DIFF": "P",
      "PAIR": "IOL17B",
      "DQS": "NONE",
      "TRUELVDS": true
    },
    {
      "INDEX": "30",
      "NAME": "IOL17B",
      "TYPE": "I/O",
      "BANK": 8,
      "DIFF": "N",
      "PAIR": "IOL17A",
      "DQS": "NONE",
      "TRUELVDS": true
    },
    {
      "INDEX": "31",
      "NAME": "IOL18A",
      "TYPE": "I/O",
      "BANK": 8,
      "DIFF": "P",
      "PAIR": "IOL18B",
      "DQS": "NONE"
    },
    {
      "INDEX": "32",
      "NAME": "IOL18B",
      "TYPE": "I/O",
      "BANK": 8,
      "DIFF": "N",
      "PAIR": "IOL18A",
      "DQS": "NONE"
    },
    {
      "INDEX": "33",
      "NAME": "IOL19A",
      "TYPE": "I/O",
      "BANK": 8,
      "DIFF": "P",
      "PAIR": "IOL19B",
      "DQS": "NONE",
      "TRUELVDS": true
    },
    {
      "INDEX": "34",
      "NAME": "IOL19B",
      "TYPE": "I/O",
      "BANK": 8,
      "DIFF": "N",
      "PAIR": "IOL19A",
      "DQS": "NONE",
      "TRUELVDS": true
    },
    {
      "INDEX": "35",
      "NAME": "IOL20A",
      "TYPE": "I/O",
      "BANK": 8,
      "DIFF": "P",
      "PAIR": "IOL20B",
      "DQS": "NONE"
    },
    {
      "INDEX": "36",
      "NAME": "IOL20B",
      "TYPE": "I/O",
      "BANK": 8,
      "DIFF": "N",
      "PAIR": "IOL20A",
      "DQS": "NONE"
    },
    {
      "INDEX": "37",
      "NAME": "IOL21A",
      "TYPE": "I/O",
      "BANK": 7,
      "DIFF": "P",
      "PAIR": "IOL21B",
      "DQS": "NONE",
      "TRUELVDS": true
    },
    {
      "INDEX": "38",
      "NAME": "IOL21B",
      "TYPE": "I/O",
      "BANK": 7,
      "DIFF": "N",
      "PAIR": "IOL21A",
      "DQS": "NONE",
      "TRUELVDS": true
    },
    {
      "INDEX": "39",
      "NAME": "IOL22A",
      "TYPE": "I/O",
      "BANK": 7,
      "DIFF": "P",
      "PAIR": "IOL22B",
      "DQS": "NONE"
    },
    {
      "INDEX": "40",
      "NAME": "IOL22B",
      "TYPE": "I/O",
      "BANK": 7,
      "DIFF": "N",
      "PAIR": "IOL22A",
      "DQS": "NONE"
    },
    {
      "INDEX": "41",
      "NAME": "IOL23A",
      "TYPE": "I/O",
      "BANK": 7,
      "DIFF": "P",
      "PAIR": "IOL23B",
      "DQS": "NONE",
      "TRUELVDS": true
    },
    {
      "INDEX": "42",
      "NAME": "IOL23B",
      "TYPE": "I/O",
      "BANK": 7,
      "DIFF": "N",
      "PAIR": "IOL23A",
      "DQS": "NONE",
      "TRUELVDS": true
    },
    {
      "INDEX": "43",
      "NAME": "IOL24A",
      "TYPE": "I/O",
      "BANK": 7,
      "DIFF": "P",
      "PAIR": "IOL24B",
      "DQS": "NONE"
    },
    {
      "INDEX": "44",
      "NAME": "IOL24B",
      "TYPE": "I/O",
      "BANK": 7,
      "DIFF": "N",
      "PAIR": "IOL24A",
      "DQS": "NONE"
    },
    {
      "INDEX": "45",
      "NAME": "IOL25A",
      "TYPE": "I/O",
      "BANK": 7,
      "CFG": "GCLKT_7",
      "DIFF": "P",
      "PAIR": "IOL25B",
      "DQS": "NONE",
      "TRUELVDS": true
    },
    {
      "INDEX": "46",
      "NAME": "IOL25B",
      "TYPE": "I/O",
      "BANK": 7,
      "CFG": "GCLKC_7",
      "DIFF": "N",
      "PAIR": "IOL25A",
      "DQS": "NONE",
      "TRUELVDS": true
    },
    {
      "INDEX": "47",
      "NAME": "IOL26A",
      "TYPE": "I/O",
      "BANK": 7,
      "DIFF": "P",
      "PAIR": "IOL26B",
      "DQS": "NONE"
    },
    {
      "INDEX": "48",
      "NAME": "IOL26B",
      "TYPE": "I/O",
      "BANK": 7,
      "DIFF": "N",
      "PAIR": "IOL26A",
      "DQS": "NONE"
    },
    {
      "INDEX": "49",
      "NAME": "IOL27A",
      "TYPE": "I/O",
      "BANK": 9,
      "CFG": "MO",
      "DIFF": "P",
      "PAIR": "IOL27B",
      "DQS": "NONE"
    },
    {
      "INDEX": "50",
      "NAME": "IOL27B",
      "TYPE": "I/O",
      "BANK": 9,
      "CFG": "MI-1",
      "DIFF": "N",
      "PAIR": "IOL27A",
      "DQS": "NONE"
    },
    {
      "INDEX": "51",
      "NAME": "IOL27C",
      "TYPE": "I/O",
      "BANK": 9,
      "CFG": "MI-2",
      "DIFF": "P",
      "PAIR": "IOL27D",
      "DQS": "NONE"
    },
    {
      "INDEX": "52",
      "NAME": "IOL27D",
      "TYPE": "I/O",
      "BANK": 9,
      "CFG": "MI-3",
      "DIFF": "N",
      "PAIR": "IOL27C",
      "DQS": "NONE"
    },
    {
      "INDEX": "53",
      "NAME": "IOL27E",
      "TYPE": "I/O",
      "BANK": 9,
      "CFG": "MCLK",
      "DIFF": "P",
      "PAIR": "IOL27F",
      "DQS": "NONE"
    },
    {
      "INDEX": "54",
      "NAME": "IOL27F",
      "TYPE": "I/O",
      "BANK": 9,
      "CFG": "MCS_N",
      "DIFF": "N",
      "PAIR": "IOL27E",
      "DQS": "NONE"
    },
    {
      "INDEX": "55",
      "NAME": "IOL28A",
      "TYPE": "I/O",
      "BANK": 7,
      "DIFF": "P",
      "PAIR": "IOL28B",
      "DQS": "NONE",
      "TRUELVDS": true
    },
    {
      "INDEX": "56",
      "NAME": "IOL28B",
      "TYPE": "I/O",
      "BANK": 7,
      "DIFF": "N",
      "PAIR": "IOL28A",
      "DQS": "NONE",
      "TRUELVDS": true
    },
    {
      "INDEX": "57",
      "NAME": "IOL29A",
      "TYPE": "I/O",
      "BANK": 7,
      "DIFF": "P",
      "PAIR": "IOL29B",
      "DQS": "NONE"
    },
    {
      "INDEX": "58",
      "NAME": "IOL29B",
      "TYPE": "I/O",
      "BANK": 7,
      "DIFF": "N",
      "PAIR": "IOL29A",
      "DQS": "NONE"
    },
    {
      "INDEX": "59",
      "NAME": "IOL30A",
      "TYPE": "I/O",
      "BANK": 7,
      "DIFF": "P",
      "PAIR": "IOL30B",
      "DQS": "NONE",
      "TRUELVDS": true
    },
    {
      "INDEX": "60",
      "NAME": "IOL30B",
      "TYPE": "I/O",
      "BANK": 7,
      "DIFF": "N",
      "PAIR": "IOL30A",
      "DQS": "NONE",
      "TRUELVDS": true
    },
    {
      "INDEX": "61",
      "NAME": "IOL31A",
      "TYPE": "I/O",
      "BANK": 7,
      "DIFF": "P",
      "PAIR": "IOL31B",
      "DQS": "NONE"
    },
    {
      "INDEX": "62",
      "NAME": "IOL31B",
      "TYPE": "I/O",
      "BANK": 7,
      "DIFF": "N",
      "PAIR": "IOL31A",
      "DQS": "NONE"
    },
    {
      "INDEX": "63",
      "NAME": "IOL32A",
      "TYPE": "I/O",
      "BANK": 7,
      "DIFF": "P",
      "PAIR": "IOL32B",
      "DQS": "NONE",
      "TRUELVDS": true
    },
    {
      "INDEX": "64",
      "NAME": "IOL32B",
      "TYPE": "I/O",
      "BANK": 7,
      "DIFF": "N",
      "PAIR": "IOL32A",
      "DQS": "NONE",
      "TRUELVDS": true
    },
    {
      "INDEX": "65",
      "NAME": "IOL33A",
      "TYPE": "I/O",
      "BANK": 7,
      "DIFF": "P",
      "PAIR": "IOL33B",
      "DQS": "NONE"
    },
    {
      "INDEX": "66",
      "NAME": "IOL33B",
      "TYPE": "I/O",
      "BANK": 7,
      "DIFF": "N",
      "PAIR": "IOL33A",
      "DQS": "NONE"
    },
    {
      "INDEX": "67",
      "NAME": "IOL34A",
      "TYPE": "I/O",
      "BANK": 6,
      "DIFF": "P",
      "PAIR": "IOL34B",
      "DQS": "NONE",
      "TRUELVDS": true
    },
    {
      "INDEX": "68",
      "NAME": "IOL34B",
      "TYPE": "I/O",
      "BANK": 6,
      "DIFF": "N",
      "PAIR": "IOL34A",
      "DQS": "NONE",
      "TRUELVDS": true
    },
    {
      "INDEX": "69",
      "NAME": "IOL35A",
      "TYPE": "I/O",
      "BANK": 6,
      "DIFF": "P",
      "PAIR": "IOL35B",
      "DQS": "NONE"
    },
    {
      "INDEX": "70",
      "NAME": "IOL35B",
      "TYPE": "I/O",
      "BANK": 6,
      "DIFF": "N",
      "PAIR": "IOL35A",
      "DQS": "NONE"
    },
    {
      "INDEX": "71",
      "NAME": "IOL36A",
      "TYPE": "I/O",
      "BANK": 6,
      "DIFF": "P",
      "PAIR": "IOL36B",
      "DQS": "NONE",
      "TRUELVDS": true
    },
    {
      "INDEX": "72",
      "NAME": "IOL36B",
      "TYPE": "I/O",
      "BANK": 6,
      "DIFF": "N",
      "PAIR": "IOL36A",
      "DQS": "NONE",
      "TRUELVDS": true
    },
    {
      "INDEX": "73",
      "NAME": "IOL37A",
      "TYPE": "I/O",
      "BANK": 6,
      "DIFF": "P",
      "PAIR": "IOL37B",
      "DQS": "NONE"
    },
    {
      "INDEX": "74",
      "NAME": "IOL37B",
      "TYPE": "I/O",
      "BANK": 6,
      "DIFF": "N",
      "PAIR": "IOL37A",
      "DQS": "NONE"
    },
    {
      "INDEX": "75",
      "NAME": "IOL38A",
      "TYPE": "I/O",
      "BANK": 6,
      "DIFF": "P",
      "PAIR": "IOL38B",
      "DQS": "NONE",
      "TRUELVDS": true
    },
    {
      "INDEX": "76",
      "NAME": "IOL38B",
      "TYPE": "I/O",
      "BANK": 6,
      "DIFF": "N",
      "PAIR": "IOL38A",
      "DQS": "NONE",
      "TRUELVDS": true
    },
    {
      "INDEX": "77",
      "NAME": "IOL39A",
      "TYPE": "I/O",
      "BANK": 6,
      "DIFF": "P",
      "PAIR": "IOL39B",
      "DQS": "NONE"
    },
    {
      "INDEX": "78",
      "NAME": "IOL39B",
      "TYPE": "I/O",
      "BANK": 6,
      "DIFF": "N",
      "PAIR": "IOL39A",
      "DQS": "NONE"
    },
    {
      "INDEX": "79",
      "NAME": "IOL40A",
      "TYPE": "I/O",
      "BANK": 6,
      "DIFF": "P",
      "PAIR": "IOL40B",
      "DQS": "NONE",
      "TRUELVDS": true
    },
    {
      "INDEX": "80",
      "NAME": "IOL40B",
      "TYPE": "I/O",
      "BANK": 6,
      "DIFF": "N",
      "PAIR": "IOL40A",
      "DQS": "NONE",
      "TRUELVDS": true
    },
    {
      "INDEX": "81",
      "NAME": "IOL41A",
      "TYPE": "I/O",
      "BANK": 6,
      "DIFF": "P",
      "PAIR": "IOL41B",
      "DQS": "NONE"
    },
    {
      "INDEX": "82",
      "NAME": "IOL41B",
      "TYPE": "I/O",
      "BANK": 6,
      "DIFF": "N",
      "PAIR": "IOL41A",
      "DQS": "NONE"
    },
    {
      "INDEX": "83",
      "NAME": "IOL42A",
      "TYPE": "I/O",
      "BANK": 6,
      "DIFF": "P",
      "PAIR": "IOL42B",
      "DQS": "NONE",
      "TRUELVDS": true
    },
    {
      "INDEX": "84",
      "NAME": "IOL42B",
      "TYPE": "I/O",
      "BANK": 6,
      "DIFF": "N",
      "PAIR": "IOL42A",
      "DQS": "NONE",
      "TRUELVDS": true
    },
    {
      "INDEX": "85",
      "NAME": "IOL43A",
      "TYPE": "I/O",
      "BANK": 6,
      "DIFF": "P",
      "PAIR": "IOL43B",
      "DQS": "NONE"
    },
    {
      "INDEX": "86",
      "NAME": "IOL43B",
      "TYPE": "I/O",
      "BANK": 6,
      "DIFF": "N",
      "PAIR": "IOL43A",
      "DQS": "NONE"
    },
    {
      "INDEX": "87",
      "NAME": "IOL44A",
      "TYPE": "I/O",
      "BANK": 6,
      "CFG": "GCLKT_6",
      "DIFF": "P",
      "PAIR": "IOL44B",
      "DQS": "NONE",
      "TRUELVDS": true
    },
    {
      "INDEX": "88",
      "NAME": "IOL44B",
      "TYPE": "I/O",
      "BANK": 6,
      "CFG": "GCLKC_6",
      "DIFF": "N",
      "PAIR": "IOL44A",
      "DQS": "NONE",
      "TRUELVDS": true
    },
    {
      "INDEX": "89",
      "NAME": "IOL45A",
      "TYPE": "I/O",
      "BANK": 6,
      "DIFF": "P",
      "PAIR": "IOL45B",
      "DQS": "NONE"
    },
    {
      "INDEX": "90",
      "NAME": "IOL45B",
      "TYPE": "I/O",
      "BANK": 6,
      "DIFF": "N",
      "PAIR": "IOL45A",
      "DQS": "NONE"
    },
    {
      "INDEX": "91",
      "NAME": "IOL46A",
      "TYPE": "I/O",
      "BANK": 6,
      "DIFF": "P",
      "PAIR": "IOL46B",
      "DQS": "NONE",
      "TRUELVDS": true
    },
    {
      "INDEX": "92",
      "NAME": "IOL46B",
      "TYPE": "I/O",
      "BANK": 6,
      "DIFF": "N",
      "PAIR": "IOL46A",
      "DQS": "NONE",
      "TRUELVDS": true
    },
    {
      "INDEX": "93",
      "NAME": "IOL47A",
      "TYPE": "I/O",
      "BANK": 6,
      "DIFF": "P",
      "PAIR": "IOL47B",
      "DQS": "NONE"
    },
    {
      "INDEX": "94",
      "NAME": "IOL47B",
      "TYPE": "I/O",
      "BANK": 6,
      "DIFF": "N",
      "PAIR": "IOL47A",
      "DQS": "NONE"
    },
    {
      "INDEX": "95",
      "NAME": "IOL48A",
      "TYPE": "I/O",
      "BANK": 6,
      "DIFF": "P",
      "PAIR": "IOL48B",
      "DQS": "NONE",
      "TRUELVDS": true
    },
    {
      "INDEX": "96",
      "NAME": "IOL48B",
      "TYPE": "I/O",
      "BANK": 6,
      "DIFF": "N",
      "PAIR": "IOL48A",
      "DQS": "NONE",
      "TRUELVDS": true
    },
    {
      "INDEX": "97",
      "NAME": "IOL49A",
      "TYPE": "I/O",
      "BANK": 6,
      "DIFF": "P",
      "PAIR": "IOL49B",
      "DQS": "NONE"
    },
    {
      "INDEX": "98",
      "NAME": "IOL49B",
      "TYPE": "I/O",
      "BANK": 6,
      "DIFF": "N",
      "PAIR": "IOL49A",
      "DQS": "NONE"
    },
    {
      "INDEX": "99",
      "NAME": "IOL50A",
      "TYPE": "I/O",
      "BANK": 6,
      "DIFF": "P",
      "PAIR": "IOL50B",
      "DQS": "NONE",
      "TRUELVDS": true
    },
    {
      "INDEX": "100",
      "NAME": "IOL50B",
      "TYPE": "I/O",
      "BANK": 6,
      "DIFF": "N",
      "PAIR": "IOL50A",
      "DQS": "NONE",
      "TRUELVDS": true
    },
    {
      "INDEX": "101",
      "NAME": "IOL51A",
      "TYPE": "I/O",
      "BANK": 6,
      "DIFF": "P",
      "PAIR": "IOL51B",
      "DQS": "NONE"
    },
    {
      "INDEX": "102",
      "NAME": "IOL51B",
      "TYPE": "I/O",
      "BANK": 6,
      "DIFF": "N",
      "PAIR": "IOL51A",
      "DQS": "NONE"
    },
    {
      "INDEX": "103",
      "NAME": "IOB2A",
      "TYPE": "I/O",
      "BANK": 5,
      "DIFF": "P",
      "PAIR": "IOB2B",
      "DQS": "DQ1",
      "TRUELVDS": true
    },
    {
      "INDEX": "104",
      "NAME": "IOB2B",
      "TYPE": "I/O",
      "BANK": 5,
      "DIFF": "N",
      "PAIR": "IOB2A",
      "DQS": "DQ1",
      "TRUELVDS": true
    },
    {
      "INDEX": "105",
      "NAME": "IOB3A",
      "TYPE": "I/O",
      "BANK": 5,
      "DIFF": "P",
      "PAIR": "IOB3B",
      "DQS": "DQ1"
    },
    {
      "INDEX": "106",
      "NAME": "IOB3B",
      "TYPE": "I/O",
      "BANK": 5,
      "DIFF": "N",
      "PAIR": "IOB3A",
      "DQS": "DQ1"
    },
    {
      "INDEX": "107",
      "NAME": "IOB4A",
      "TYPE": "I/O",
      "BANK": 5,
      "DIFF": "P",
      "PAIR": "IOB4B",
      "DQS": "DQ1",
      "TRUELVDS": true
    },
    {
      "INDEX": "108",
      "NAME": "IOB4B",
      "TYPE": "I/O",
      "BANK": 5,
      "DIFF": "N",
      "PAIR": "IOB4A",
      "DQS": "DQ1",
      "TRUELVDS": true
    },
    {
      "INDEX": "109",
      "NAME": "IOB5A",
      "TYPE": "I/O",
      "BANK": 5,
      "DIFF": "P",
      "PAIR": "IOB5B",
      "DQS": "DQ1"
    },
    {
      "INDEX": "110",
      "NAME": "IOB5B",
      "TYPE": "I/O",
      "BANK": 5,
      "DIFF": "N",
      "PAIR": "IOB5A",
      "DQS": "DQ1"
    },
    {
      "INDEX": "111",
      "NAME": "IOB6A",
      "TYPE": "I/O",
      "BANK": 5,
      "DIFF": "P",
      "PAIR": "IOB6B",
      "DQS": "DQ1",
      "TRUELVDS": true
    },
    {
      "INDEX": "112",
      "NAME": "IOB6B",
      "TYPE": "I/O",
      "BANK": 5,
      "DIFF": "N",
      "PAIR": "IOB6A",
      "DQS": "DQ1",
      "TRUELVDS": true
    },
    {
      "INDEX": "113",
      "NAME": "IOB7A",
      "TYPE": "I/O",
      "BANK": 5,
      "DIFF": "P",
      "PAIR": "IOB7B",
      "DQS": "DQ1"
    },
    {
      "INDEX": "114",
      "NAME": "IOB7B",
      "TYPE": "I/O",
      "BANK": 5,
      "DIFF": "N",
      "PAIR": "IOB7A",
      "DQS": "DQ1"
    },
    {
      "INDEX": "115",
      "NAME": "IOB8A",
      "TYPE": "I/O",
      "BANK": 5,
      "DIFF": "P",
      "PAIR": "IOB8B",
      "DQS": "DQ1",
      "TRUELVDS": true
    },
    {
      "INDEX": "116",
      "NAME": "IOB8B",
      "TYPE": "I/O",
      "BANK": 5,
      "DIFF": "N",
      "PAIR": "IOB8A",
      "DQS": "DQ1",
      "TRUELVDS": true
    },
    {
      "INDEX": "117",
      "NAME": "IOB9A",
      "TYPE": "I/O",
      "BANK": 5,
      "DIFF": "P",
      "PAIR": "IOB9B",
      "DQS": "DQS1"
    },
    {
      "INDEX": "118",
      "NAME": "IOB9B",
      "TYPE": "I/O",
      "BANK": 5,
      "DIFF": "N",
      "PAIR": "IOB9A",
      "DQS": "DQS1"
    },
    {
      "INDEX": "119",
      "NAME": "IOB12A",
      "TYPE": "I/O",
      "BANK": 5,
      "DIFF": "P",
      "PAIR": "IOB12B",
      "DQS": "DQ2",
      "TRUELVDS": true
    },
    {
      "INDEX": "120",
      "NAME": "IOB12B",
      "TYPE": "I/O",
      "BANK": 5,
      "DIFF": "N",
      "PAIR": "IOB12A",
      "DQS": "DQ2",
      "TRUELVDS": true
    },
    {
      "INDEX": "121",
      "NAME": "IOB13A",
      "TYPE": "I/O",
      "BANK": 5,
      "DIFF": "P",
      "PAIR": "IOB13B",
      "DQS": "DQ2"
    },
    {
      "INDEX": "122",
      "NAME": "IOB13B",
      "TYPE": "I/O",
      "BANK": 5,
      "DIFF": "N",
      "PAIR": "IOB13A",
      "DQS": "DQ2"
    },
    {
      "INDEX": "123",
      "NAME": "IOB14A",
      "TYPE": "I/O",
      "BANK": 5,
      "DIFF": "P",
      "PAIR": "IOB14B",
      "DQS": "DQ2",
      "TRUELVDS": true
    },
    {
      "INDEX": "124",
      "NAME": "IOB14B",
      "TYPE": "I/O",
      "BANK": 5,
      "DIFF": "N",
      "PAIR": "IOB14A",
      "DQS": "DQ2",
      "TRUELVDS": true
    },
    {
      "INDEX": "125",
      "NAME": "IOB15A",
      "TYPE": "I/O",
      "BANK": 5,
      "DIFF": "P",
      "PAIR": "IOB15B",
      "DQS": "DQ2"
    },
    {
      "INDEX": "126",
      "NAME": "IOB15B",
      "TYPE": "I/O",
      "BANK": 5,
      "DIFF": "N",
      "PAIR": "IOB15A",
      "DQS": "DQ2"
    },
    {
      "INDEX": "127",
      "NAME": "IOB16A",
      "TYPE": "I/O",
      "BANK": 5,
      "DIFF": "P",
      "PAIR": "IOB16B",
      "DQS": "DQ2",
      "TRUELVDS": true
    },
    {
      "INDEX": "128",
      "NAME": "IOB16B",
      "TYPE": "I/O",
      "BANK": 5,
      "DIFF": "N",
      "PAIR": "IOB16A",
      "DQS": "DQ2",
      "TRUELVDS": true
    },
    {
      "INDEX": "129",
      "NAME": "IOB17A",
      "TYPE": "I/O",
      "BANK": 5,
      "DIFF": "P",
      "PAIR": "IOB17B",
      "DQS": "DQ2"
    },
    {
      "INDEX": "130",
      "NAME": "IOB17B",
      "TYPE": "I/O",
      "BANK": 5,
      "DIFF": "N",
      "PAIR": "IOB17A",
      "DQS": "DQ2"
    },
    {
      "INDEX": "131",
      "NAME": "IOB18A",
      "TYPE": "I/O",
      "BANK": 5,
      "DIFF": "P",
      "PAIR": "IOB18B",
      "DQS": "DQ2",
      "TRUELVDS": true
    },
    {
      "INDEX": "132",
      "NAME": "IOB18B",
      "TYPE": "I/O",
      "BANK": 5,
      "DIFF": "N",
      "PAIR": "IOB18A",
      "DQS": "DQ2",
      "TRUELVDS": true
    },
    {
      "INDEX": "133",
      "NAME": "IOB19A",
      "TYPE": "I/O",
      "BANK": 5,
      "DIFF": "P",
      "PAIR": "IOB19B",
      "DQS": "DQ2"
    },
    {
      "INDEX": "134",
      "NAME": "IOB19B",
      "TYPE": "I/O",
      "BANK": 5,
      "DIFF": "N",
      "PAIR": "IOB19A",
      "DQS": "DQ2"
    },
    {
      "INDEX": "135",
      "NAME": "IOB20A",
      "TYPE": "I/O",
      "BANK": 5,
      "DIFF": "P",
      "PAIR": "IOB20B",
      "DQS": "DQ2",
      "TRUELVDS": true
    },
    {
      "INDEX": "136",
      "NAME": "IOB20B",
      "TYPE": "I/O",
      "BANK": 5,
      "DIFF": "N",
      "PAIR": "IOB20A",
      "DQS": "DQ2",
      "TRUELVDS": true
    },
    {
      "INDEX": "137",
      "NAME": "IOB21A",
      "TYPE": "I/O",
      "BANK": 5,
      "DIFF": "P",
      "PAIR": "IOB21B",
      "DQS": "DQS2"
    },
    {
      "INDEX": "138",
      "NAME": "IOB21B",
      "TYPE": "I/O",
      "BANK": 5,
      "DIFF": "N",
      "PAIR": "IOB21A",
      "DQS": "DQS2"
    },
    {
      "INDEX": "139",
      "NAME": "IOB22A",
      "TYPE": "I/O",
      "BANK": 5,
      "DIFF": "P",
      "PAIR": "IOB22B",
      "DQS": "DQ2",
      "TRUELVDS": true
    },
    {
      "INDEX": "140",
      "NAME": "IOB22B",
      "TYPE": "I/O",
      "BANK": 5,
      "DIFF": "N",
      "PAIR": "IOB22A",
      "DQS": "DQ2",
      "TRUELVDS": true
    },
    {
      "INDEX": "141",
      "NAME": "IOB23A",
      "TYPE": "I/O",
      "BANK": 5,
      "CFG": "GCLKT_5",
      "DIFF": "P",
      "PAIR": "IOB23B",
      "DQS": "DQ2"
    },
    {
      "INDEX": "142",
      "NAME": "IOB23B",
      "TYPE": "I/O",
      "BANK": 5,
      "CFG": "GCLKC_5",
      "DIFF": "N",
      "PAIR": "IOB23A",
      "DQS": "DQ2"
    },
    {
      "INDEX": "143",
      "NAME": "IOB24A",
      "TYPE": "I/O",
      "BANK": 5,
      "DIFF": "P",
      "PAIR": "IOB24B",
      "DQS": "DQ2",
      "TRUELVDS": true
    },
    {
      "INDEX": "144",
      "NAME": "IOB24B",
      "TYPE": "I/O",
      "BANK": 5,
      "DIFF": "N",
      "PAIR": "IOB24A",
      "DQS": "DQ2",
      "TRUELVDS": true
    },
    {
      "INDEX": "145",
      "NAME": "IOB25A",
      "TYPE": "I/O",
      "BANK": 5,
      "DIFF": "P",
      "PAIR": "IOB25B",
      "DQS": "DQ2"
    },
    {
      "INDEX": "146",
      "NAME": "IOB25B",
      "TYPE": "I/O",
      "BANK": 5,
      "DIFF": "N",
      "PAIR": "IOB25A",
      "DQS": "DQ2"
    },
    {
      "INDEX": "147",
      "NAME": "IOB26A",
      "TYPE": "I/O",
      "BANK": 5,
      "DIFF": "P",
      "PAIR": "IOB26B",
      "DQS": "DQ2",
      "TRUELVDS": true
    },
    {
      "INDEX": "148",
      "NAME": "IOB26B",
      "TYPE": "I/O",
      "BANK": 5,
      "DIFF": "N",
      "PAIR": "IOB26A",
      "DQS": "DQ2",
      "TRUELVDS": true
    },
    {
      "INDEX": "149",
      "NAME": "IOB27A",
      "TYPE": "I/O",
      "BANK": 5,
      "DIFF": "P",
      "PAIR": "IOB27B",
      "DQS": "DQ2"
    },
    {
      "INDEX": "150",
      "NAME": "IOB27B",
      "TYPE": "I/O",
      "BANK": 5,
      "DIFF": "N",
      "PAIR": "IOB27A",
      "DQS": "DQ2"
    },
    {
      "INDEX": "151",
      "NAME": "IOB28A",
      "TYPE": "I/O",
      "BANK": 5,
      "CFG": "MODE0",
      "DIFF": "P",
      "PAIR": "IOB28B",
      "DQS": "NONE"
    },
    {
      "INDEX": "152",
      "NAME": "IOB28B",
      "TYPE": "I/O",
      "BANK": 5,
      "CFG": "MODE1",
      "DIFF": "N",
      "PAIR": "IOB28A",
      "DQS": "NONE"
    },
    {
      "INDEX": "153",
      "NAME": "IOB30A",
      "TYPE": "I/O",
      "BANK": 4,
      "CFG": "GCLKT_4",
      "DIFF": "P",
      "PAIR": "IOB30B",
      "DQS": "DQ3",
      "TRUELVDS": true
    },
    {
      "INDEX": "154",
      "NAME": "IOB30B",
      "TYPE": "I/O",
      "BANK": 4,
      "CFG": "GCLKC_4",
      "DIFF": "N",
      "PAIR": "IOB30A",
      "DQS": "DQ3",
      "TRUELVDS": true
    },
    {
      "INDEX": "155",
      "NAME": "IOB31A",
      "TYPE": "I/O",
      "BANK": 4,
      "DIFF": "P",
      "PAIR": "IOB31B",
      "DQS": "DQ3"
    },
    {
      "INDEX": "156",
      "NAME": "IOB31B",
      "TYPE": "I/O",
      "BANK": 4,
      "DIFF": "N",
      "PAIR": "IOB31A",
      "DQS": "DQ3"
    },
    {
      "INDEX": "157",
      "NAME": "IOB32A",
      "TYPE": "I/O",
      "BANK": 4,
      "DIFF": "P",
      "PAIR": "IOB32B",
      "DQS": "DQ3",
      "TRUELVDS": true
    },
    {
      "INDEX": "158",
      "NAME": "IOB32B",
      "TYPE": "I/O",
      "BANK": 4,
      "DIFF": "N",
      "PAIR": "IOB32A",
      "DQS": "DQ3",
      "TRUELVDS": true
    },
    {
      "INDEX": "159",
      "NAME": "IOB33A",
      "TYPE": "I/O",
      "BANK": 4,
      "DIFF": "P",
      "PAIR": "IOB33B",
      "DQS": "DQ3"
    },
    {
      "INDEX": "160",
      "NAME": "IOB33B",
      "TYPE": "I/O",
      "BANK": 4,
      "DIFF": "N",
      "PAIR": "IOB33A",
      "DQS": "DQ3"
    },
    {
      "INDEX": "161",
      "NAME": "IOB34A",
      "TYPE": "I/O",
      "BANK": 4,
      "DIFF": "P",
      "PAIR": "IOB34B",
      "DQS": "DQ3",
      "TRUELVDS": true
    },
    {
      "INDEX": "162",
      "NAME": "IOB34B",
      "TYPE": "I/O",
      "BANK": 4,
      "DIFF": "N",
      "PAIR": "IOB34A",
      "DQS": "DQ3",
      "TRUELVDS": true
    },
    {
      "INDEX": "163",
      "NAME": "IOB35A",
      "TYPE": "I/O",
      "BANK": 4,
      "DIFF": "P",
      "PAIR": "IOB35B",
      "DQS": "DQ3"
    },
    {
      "INDEX": "164",
      "NAME": "IOB35B",
      "TYPE": "I/O",
      "BANK": 4,
      "DIFF": "N",
      "PAIR": "IOB35A",
      "DQS": "DQ3"
    },
    {
      "INDEX": "165",
      "NAME": "IOB36A",
      "TYPE": "I/O",
      "BANK": 4,
      "DIFF": "P",
      "PAIR": "IOB36B",
      "DQS": "DQ3",
      "TRUELVDS": true
    },
    {
      "INDEX": "166",
      "NAME": "IOB36B",
      "TYPE": "I/O",
      "BANK": 4,
      "DIFF": "N",
      "PAIR": "IOB36A",
      "DQS": "DQ3",
      "TRUELVDS": true
    },
    {
      "INDEX": "167",
      "NAME": "IOB37A",
      "TYPE": "I/O",
      "BANK": 4,
      "DIFF": "P",
      "PAIR": "IOB37B",
      "DQS": "DQS3"
    },
    {
      "INDEX": "168",
      "NAME": "IOB37B",
      "TYPE": "I/O",
      "BANK": 4,
      "DIFF": "N",
      "PAIR": "IOB37A",
      "DQS": "DQS3"
    },
    {
      "INDEX": "169",
      "NAME": "IOB38A",
      "TYPE": "I/O",
      "BANK": 4,
      "DIFF": "P",
      "PAIR": "IOB38B",
      "DQS": "DQ3",
      "TRUELVDS": true
    },
    {
      "INDEX": "170",
      "NAME": "IOB38B",
      "TYPE": "I/O",
      "BANK": 4,
      "DIFF": "N",
      "PAIR": "IOB38A",
      "DQS": "DQ3",
      "TRUELVDS": true
    },
    {
      "INDEX": "171",
      "NAME": "IOB39A",
      "TYPE": "I/O",
      "BANK": 4,
      "DIFF": "P",
      "PAIR": "IOB39B",
      "DQS": "DQ3"
    },
    {
      "INDEX": "172",
      "NAME": "IOB39B",
      "TYPE": "I/O",
      "BANK": 4,
      "DIFF": "N",
      "PAIR": "IOB39A",
      "DQS": "DQ3"
    },
    {
      "INDEX": "173",
      "NAME": "IOB40A",
      "TYPE": "I/O",
      "BANK": 4,
      "DIFF": "P",
      "PAIR": "IOB40B",
      "DQS": "DQ3",
      "TRUELVDS": true
    },
    {
      "INDEX": "174",
      "NAME": "IOB40B",
      "TYPE": "I/O",
      "BANK": 4,
      "DIFF": "N",
      "PAIR": "IOB40A",
      "DQS": "DQ3",
      "TRUELVDS": true
    },
    {
      "INDEX": "175",
      "NAME": "IOB41A",
      "TYPE": "I/O",
      "BANK": 4,
      "DIFF": "P",
      "PAIR": "IOB41B",
      "DQS": "DQ3"
    },
    {
      "INDEX": "176",
      "NAME": "IOB41B",
      "TYPE": "I/O",
      "BANK": 4,
      "DIFF": "N",
      "PAIR": "IOB41A",
      "DQS": "DQ3"
    },
    {
      "INDEX": "177",
      "NAME": "IOB42A",
      "TYPE": "I/O",
      "BANK": 4,
      "DIFF": "P",
      "PAIR": "IOB42B",
      "DQS": "DQ3",
      "TRUELVDS": true
    },
    {
      "INDEX": "178",
      "NAME": "IOB42B",
      "TYPE": "I/O",
      "BANK": 4,
      "DIFF": "N",
      "PAIR": "IOB42A",
      "DQS": "DQ3",
      "TRUELVDS": true
    },
    {
      "INDEX": "179",
      "NAME": "IOB43A",
      "TYPE": "I/O",
      "BANK": 4,
      "DIFF": "P",
      "PAIR": "IOB43B",
      "DQS": "DQ3"
    },
    {
      "INDEX": "180",
      "NAME": "IOB43B",
      "TYPE": "I/O",
      "BANK": 4,
      "DIFF": "N",
      "PAIR": "IOB43A",
      "DQS": "DQ3"
    },
    {
      "INDEX": "181",
      "NAME": "IOB44A",
      "TYPE": "I/O",
      "BANK": 4,
      "DIFF": "P",
      "PAIR": "IOB44B",
      "DQS": "DQ3",
      "TRUELVDS": true
    },
    {
      "INDEX": "182",
      "NAME": "IOB44B",
      "TYPE": "I/O",
      "BANK": 4,
      "DIFF": "N",
      "PAIR": "IOB44A",
      "DQS": "DQ3",
      "TRUELVDS": true
    },
    {
      "INDEX": "183",
      "NAME": "IOB45A",
      "TYPE": "I/O",
      "BANK": 4,
      "DIFF": "P",
      "PAIR": "IOB45B",
      "DQS": "DQ3"
    },
    {
      "INDEX": "184",
      "NAME": "IOB45B",
      "TYPE": "I/O",
      "BANK": 4,
      "DIFF": "N",
      "PAIR": "IOB45A",
      "DQS": "DQ3"
    },
    {
      "INDEX": "185",
      "NAME": "IOB48A",
      "TYPE": "I/O",
      "BANK": 4,
      "DIFF": "P",
      "PAIR": "IOB48B",
      "DQS": "DQS4",
      "TRUELVDS": true
    },
    {
      "INDEX": "186",
      "NAME": "IOB48B",
      "TYPE": "I/O",
      "BANK": 4,
      "DIFF": "N",
      "PAIR": "IOB48A",
      "DQS": "DQS4",
      "TRUELVDS": true
    },
    {
      "INDEX": "187",
      "NAME": "IOB49A",
      "TYPE": "I/O",
      "BANK": 4,
      "DIFF": "P",
      "PAIR": "IOB49B",
      "DQS": "DQ4"
    },
    {
      "INDEX": "188",
      "NAME": "IOB49B",
      "TYPE": "I/O",
      "BANK": 4,
      "DIFF": "N",
      "PAIR": "IOB49A",
      "DQS": "DQ4"
    },
    {
      "INDEX": "189",
      "NAME": "IOB50A",
      "TYPE": "I/O",
      "BANK": 4,
      "CFG": "SCLK",
      "DIFF": "P",
      "PAIR": "IOB50B",
      "DQS": "DQ4",
      "TRUELVDS": true
    },
    {
      "INDEX": "190",
      "NAME": "IOB50B",
      "TYPE": "I/O",
      "BANK": 4,
      "CFG": "D1/SO",
      "DIFF": "N",
      "PAIR": "IOB50A",
      "DQS": "DQ4",
      "TRUELVDS": true
    },
    {
      "INDEX": "191",
      "NAME": "IOB51A",
      "TYPE": "I/O",
      "BANK": 4,
      "CFG": "DIN/CLKHOLD_N",
      "DIFF": "P",
      "PAIR": "IOB51B",
      "DQS": "DQ4"
    },
    {
      "INDEX": "192",
      "NAME": "IOB51B",
      "TYPE": "I/O",
      "BANK": 4,
      "CFG": "DOUT/WE_N",
      "DIFF": "N",
      "PAIR": "IOB51A",
      "DQS": "DQ4"
    },
    {
      "INDEX": "193",
      "NAME": "IOB52A",
      "TYPE": "I/O",
      "BANK": 4,
      "CFG": "FASTRD_N/D3",
      "DIFF": "P",
      "PAIR": "IOB52B",
      "DQS": "DQ4",
      "TRUELVDS": true
    },
    {
      "INDEX": "194",
      "NAME": "IOB52B",
      "TYPE": "I/O",
      "BANK": 4,
      "CFG": "QSSPI_WPN",
      "DIFF": "N",
      "PAIR": "IOB52A",
      "DQS": "DQ4",
      "TRUELVDS": true
    },
    {
      "INDEX": "195",
      "NAME": "IOB53A",
      "TYPE": "I/O",
      "BANK": 4,
      "CFG": "D7",
      "DIFF": "P",
      "PAIR": "IOB53B",
      "DQS": "DQ4"
    },
    {
      "INDEX": "196",
      "NAME": "IOB53B",
      "TYPE": "I/O",
      "BANK": 4,
      "CFG": "D6",
      "DIFF": "N",
      "PAIR": "IOB53A",
      "DQS": "DQ4"
    },
    {
      "INDEX": "197",
      "NAME": "IOB54A",
      "TYPE": "I/O",
      "BANK": 4,
      "CFG": "SSPI_CS_N/D0",
      "DIFF": "P",
      "PAIR": "IOB54B",
      "DQS": "DQ4",
      "TRUELVDS": true
    },
    {
      "INDEX": "198",
      "NAME": "IOB54B",
      "TYPE": "I/O",
      "BANK": 4,
      "CFG": "SI/D2",
      "DIFF": "N",
      "PAIR": "IOB54A",
      "DQS": "DQ4",
      "TRUELVDS": true
    },
    {
      "INDEX": "199",
      "NAME": "IOB55A",
      "TYPE": "I/O",
      "BANK": 4,
      "CFG": "D5",
      "DIFF": "P",
      "PAIR": "IOB55B",
      "DQS": "DQ4"
    },
    {
      "INDEX": "200",
      "NAME": "IOB55B",
      "TYPE": "I/O",
      "BANK": 4,
      "CFG": "D4",
      "DIFF": "N",
      "PAIR": "IOB55A",
      "DQS": "DQ4"
    },
    {
      "INDEX": "201",
      "NAME": "IOR51B",
      "TYPE": "I/O",
      "BANK": 3,
      "DIFF": "N",
      "PAIR": "IOR51A",
      "DQS": "NONE"
    },
    {
      "INDEX": "202",
      "NAME": "IOR51A",
      "TYPE": "I/O",
      "BANK": 3,
      "DIFF": "P",
      "PAIR": "IOR51B",
      "DQS": "NONE"
    },
    {
      "INDEX": "203",
      "NAME": "IOR50B",
      "TYPE": "I/O",
      "BANK": 3,
      "DIFF": "N",
      "PAIR": "IOR50A",
      "DQS": "NONE",
      "TRUELVDS": true
    },
    {
      "INDEX": "204",
      "NAME": "IOR50A",
      "TYPE": "I/O",
      "BANK": 3,
      "DIFF": "P",
      "PAIR": "IOR50B",
      "DQS": "NONE",
      "TRUELVDS": true
    },
    {
      "INDEX": "205",
      "NAME": "IOR49B",
      "TYPE": "I/O",
      "BANK": 3,
      "DIFF": "N",
      "PAIR": "IOR49A",
      "DQS": "NONE"
    },
    {
      "INDEX": "206",
      "NAME": "IOR49A",
      "TYPE": "I/O",
      "BANK": 3,
      "DIFF": "P",
      "PAIR": "IOR49B",
      "DQS": "NONE"
    },
    {
      "INDEX": "207",
      "NAME": "IOR48B",
      "TYPE": "I/O",
      "BANK": 3,
      "DIFF": "N",
      "PAIR": "IOR48A",
      "DQS": "NONE",
      "TRUELVDS": true
    },
    {
      "INDEX": "208",
      "NAME": "IOR48A",
      "TYPE": "I/O",
      "BANK": 3,
      "DIFF": "P",
      "PAIR": "IOR48B",
      "DQS": "NONE",
      "TRUELVDS": true
    },
    {
      "INDEX": "209",
      "NAME": "IOR47B",
      "TYPE": "I/O",
      "BANK": 3,
      "DIFF": "N",
      "PAIR": "IOR47A",
      "DQS": "NONE"
    },
    {
      "INDEX": "210",
      "NAME": "IOR47A",
      "TYPE": "I/O",
      "BANK": 3,
      "DIFF": "P",
      "PAIR": "IOR47B",
      "DQS": "NONE"
    },
    {
      "INDEX": "211",
      "NAME": "IOR46B",
      "TYPE": "I/O",
      "BANK": 3,
      "DIFF": "N",
      "PAIR": "IOR46A",
      "DQS": "NONE",
      "TRUELVDS": true
    },
    {
      "INDEX": "212",
      "NAME": "IOR46A",
      "TYPE": "I/O",
      "BANK": 3,
      "DIFF": "P",
      "PAIR": "IOR46B",
      "DQS": "NONE",
      "TRUELVDS": true
    },
    {
      "INDEX": "213",
      "NAME": "IOR45B",
      "TYPE": "I/O",
      "BANK": 3,
      "DIFF": "N",
      "PAIR": "IOR45A",
      "DQS": "NONE"
    },
    {
      "INDEX": "214",
      "NAME": "IOR45A",
      "TYPE": "I/O",
      "BANK": 3,
      "DIFF": "P",
      "PAIR": "IOR45B",
      "DQS": "NONE"
    },
    {
      "INDEX": "215",
      "NAME": "IOR44B",
      "TYPE": "I/O",
      "BANK": 3,
      "DIFF": "N",
      "PAIR": "IOR44A",
      "DQS": "NONE",
      "TRUELVDS": true
    },
    {
      "INDEX": "216",
      "NAME": "IOR44A",
      "TYPE": "I/O",
      "BANK": 3,
      "DIFF": "P",
      "PAIR": "IOR44B",
      "DQS": "NONE",
      "TRUELVDS": true
    },
    {
      "INDEX": "217",
      "NAME": "IOR43B",
      "TYPE": "I/O",
      "BANK": 3,
      "DIFF": "N",
      "PAIR": "IOR43A",
      "DQS": "NONE"
    },
    {
      "INDEX": "218",
      "NAME": "IOR43A",
      "TYPE": "I/O",
      "BANK": 3,
      "DIFF": "P",
      "PAIR": "IOR43B",
      "DQS": "NONE"
    },
    {
      "INDEX": "219",
      "NAME": "IOR42B",
      "TYPE": "I/O",
      "BANK": 3,
      "DIFF": "N",
      "PAIR": "IOR42A",
      "DQS": "NONE",
      "TRUELVDS": true
    },
    {
      "INDEX": "220",
      "NAME": "IOR42A",
      "TYPE": "I/O",
      "BANK": 3,
      "DIFF": "P",
      "PAIR": "IOR42B",
      "DQS": "NONE",
      "TRUELVDS": true
    },
    {
      "INDEX": "221",
      "NAME": "IOR41B",
      "TYPE": "I/O",
      "BANK": 3,
      "DIFF": "N",
      "PAIR": "IOR41A",
      "DQS": "NONE"
    },
    {
      "INDEX": "222",
      "NAME": "IOR41A",
      "TYPE": "I/O",
      "BANK": 3,
      "DIFF": "P",
      "PAIR": "IOR41B",
      "DQS": "NONE"
    },
    {
      "INDEX": "223",
      "NAME": "IOR40B",
      "TYPE": "I/O",
      "BANK": 3,
      "DIFF": "N",
      "PAIR": "IOR40A",
      "DQS": "NONE",
      "TRUELVDS": true
    },
    {
      "INDEX": "224",
      "NAME": "IOR40A",
      "TYPE": "I/O",
      "BANK": 3,
      "DIFF": "P",
      "PAIR": "IOR40B",
      "DQS": "NONE",
      "TRUELVDS": true
    },
    {
      "INDEX": "225",
      "NAME": "IOR39B",
      "TYPE": "I/O",
      "BANK": 3,
      "DIFF": "N",
      "PAIR": "IOR39A",
      "DQS": "NONE"
    },
    {
      "INDEX": "226",
      "NAME": "IOR39A",
      "TYPE": "I/O",
      "BANK": 3,
      "DIFF": "P",
      "PAIR": "IOR39B",
      "DQS": "NONE"
    },
    {
      "INDEX": "227",
      "NAME": "IOR38B",
      "TYPE": "I/O",
      "BANK": 3,
      "DIFF": "N",
      "PAIR": "IOR38A",
      "DQS": "NONE",
      "TRUELVDS": true
    },
    {
      "INDEX": "228",
      "NAME": "IOR38A",
      "TYPE": "I/O",
      "BANK": 3,
      "DIFF": "P",
      "PAIR": "IOR38B",
      "DQS": "NONE",
      "TRUELVDS": true
    },
    {
      "INDEX": "229",
      "NAME": "IOR37B",
      "TYPE": "I/O",
      "BANK": 3,
      "DIFF": "N",
      "PAIR": "IOR37A",
      "DQS": "NONE"
    },
    {
      "INDEX": "230",
      "NAME": "IOR37A",
      "TYPE": "I/O",
      "BANK": 3,
      "DIFF": "P",
      "PAIR": "IOR37B",
      "DQS": "NONE"
    },
    {
      "INDEX": "231",
      "NAME": "IOR36B",
      "TYPE": "I/O",
      "BANK": 3,
      "DIFF": "N",
      "PAIR": "IOR36A",
      "DQS": "NONE",
      "TRUELVDS": true
    },
    {
      "INDEX": "232",
      "NAME": "IOR36A",
      "TYPE": "I/O",
      "BANK": 3,
      "DIFF": "P",
      "PAIR": "IOR36B",
      "DQS": "NONE",
      "TRUELVDS": true
    },
    {
      "INDEX": "233",
      "NAME": "IOR35B",
      "TYPE": "I/O",
      "BANK": 3,
      "DIFF": "N",
      "PAIR": "IOR35A",
      "DQS": "NONE"
    },
    {
      "INDEX": "234",
      "NAME": "IOR35A",
      "TYPE": "I/O",
      "BANK": 3,
      "DIFF": "P",
      "PAIR": "IOR35B",
      "DQS": "NONE"
    },
    {
      "INDEX": "235",
      "NAME": "IOR34B",
      "TYPE": "I/O",
      "BANK": 3,
      "DIFF": "N",
      "PAIR": "IOR34A",
      "DQS": "NONE",
      "TRUELVDS": true
    },
    {
      "INDEX": "236",
      "NAME": "IOR34A",
      "TYPE": "I/O",
      "BANK": 3,
      "DIFF": "P",
      "PAIR": "IOR34B",
      "DQS": "NONE",
      "TRUELVDS": true
    },
    {
      "INDEX": "237",
      "NAME": "IOR33B",
      "TYPE": "I/O",
      "BANK": 3,
      "DIFF": "N",
      "PAIR": "IOR33A",
      "DQS": "NONE"
    },
    {
      "INDEX": "238",
      "NAME": "IOR33A",
      "TYPE": "I/O",
      "BANK": 3,
      "DIFF": "P",
      "PAIR": "IOR33B",
      "DQS": "NONE"
    },
    {
      "INDEX": "239",
      "NAME": "IOR32B",
      "TYPE": "I/O",
      "BANK": 3,
      "DIFF": "N",
      "PAIR": "IOR32A",
      "DQS": "NONE",
      "TRUELVDS": true
    },
    {
      "INDEX": "240",
      "NAME": "IOR32A",
      "TYPE": "I/O",
      "BANK": 3,
      "DIFF": "P",
      "PAIR": "IOR32B",
      "DQS": "NONE",
      "TRUELVDS": true
    },
    {
      "INDEX": "241",
      "NAME": "IOR31B",
      "TYPE": "I/O",
      "BANK": 3,
      "DIFF": "N",
      "PAIR": "IOR31A",
      "DQS": "NONE"
    },
    {
      "INDEX": "242",
      "NAME": "IOR31A",
      "TYPE": "I/O",
      "BANK": 3,
      "DIFF": "P",
      "PAIR": "IOR31B",
      "DQS": "NONE"
    },
    {
      "INDEX": "243",
      "NAME": "IOR30B",
      "TYPE": "I/O",
      "BANK": 3,
      "DIFF": "N",
      "PAIR": "IOR30A",
      "DQS": "NONE",
      "TRUELVDS": true
    },
    {
      "INDEX": "244",
      "NAME": "IOR30A",
      "TYPE": "I/O",
      "BANK": 3,
      "DIFF": "P",
      "PAIR": "IOR30B",
      "DQS": "NONE",
      "TRUELVDS": true
    },
    {
      "INDEX": "245",
      "NAME": "IOR29B",
      "TYPE": "I/O",
      "BANK": 3,
      "DIFF": "N",
      "PAIR": "IOR29A",
      "DQS": "NONE"
    },
    {
      "INDEX": "246",
      "NAME": "IOR29A",
      "TYPE": "I/O",
      "BANK": 3,
      "DIFF": "P",
      "PAIR": "IOR29B",
      "DQS": "NONE"
    },
    {
      "INDEX": "247",
      "NAME": "IOR28B",
      "TYPE": "I/O",
      "BANK": 3,
      "CFG": "GCLKC_3",
      "DIFF": "N",
      "PAIR": "IOR28A",
      "DQS": "NONE",
      "TRUELVDS": true
    },
    {
      "INDEX": "248",
      "NAME": "IOR28A",
      "TYPE": "I/O",
      "BANK": 3,
      "CFG": "GCLKT_3",
      "DIFF": "P",
      "PAIR": "IOR28B",
      "DQS": "NONE",
      "TRUELVDS": true
    },
    {
      "INDEX": "249",
      "NAME": "IOR26B",
      "TYPE": "I/O",
      "BANK": 2,
      "DIFF": "N",
      "PAIR": "IOR26A",
      "DQS": "NONE"
    },
    {
      "INDEX": "250",
      "NAME": "IOR26A",
      "TYPE": "I/O",
      "BANK": 2,
      "DIFF": "P",
      "PAIR": "IOR26B",
      "DQS": "NONE"
    },
    {
      "INDEX": "251",
      "NAME": "IOR25B",
      "TYPE": "I/O",
      "BANK": 2,
      "DIFF": "N",
      "PAIR": "IOR25A",
      "DQS": "NONE",
      "TRUELVDS": true
    },
    {
      "INDEX": "252",
      "NAME": "IOR25A",
      "TYPE": "I/O",
      "BANK": 2,
      "DIFF": "P",
      "PAIR": "IOR25B",
      "DQS": "NONE",
      "TRUELVDS": true
    },
    {
      "INDEX": "253",
      "NAME": "IOR24B",
      "TYPE": "I/O",
      "BANK": 2,
      "DIFF": "N",
      "PAIR": "IOR24A",
      "DQS": "NONE"
    },
    {
      "INDEX": "254",
      "NAME": "IOR24A",
      "TYPE": "I/O",
      "BANK": 2,
      "DIFF": "P",
      "PAIR": "IOR24B",
      "DQS": "NONE"
    },
    {
      "INDEX": "255",
      "NAME": "IOR23B",
      "TYPE": "I/O",
      "BANK": 2,
      "DIFF": "N",
      "PAIR": "IOR23A",
      "DQS": "NONE",
      "TRUELVDS": true
    },
    {
      "INDEX": "256",
      "NAME": "IOR23A",
      "TYPE": "I/O",
      "BANK": 2,
      "DIFF": "P",
      "PAIR": "IOR23B",
      "DQS": "NONE",
      "TRUELVDS": true
    },
    {
      "INDEX": "257",
      "NAME": "IOR22B",
      "TYPE": "I/O",
      "BANK": 2,
      "DIFF": "N",
      "PAIR": "IOR22A",
      "DQS": "NONE"
    },
    {
      "INDEX": "258",
      "NAME": "IOR22A",
      "TYPE": "I/O",
      "BANK": 2,
      "DIFF": "P",
      "PAIR": "IOR22B",
      "DQS": "NONE"
    },
    {
      "INDEX": "259",
      "NAME": "IOR21B",
      "TYPE": "I/O",
      "BANK": 2,
      "DIFF": "N",
      "PAIR": "IOR21A",
      "DQS": "NONE",
      "TRUELVDS": true
    },
    {
      "INDEX": "260",
      "NAME": "IOR21A",
      "TYPE": "I/O",
      "BANK": 2,
      "DIFF": "P",
      "PAIR": "IOR21B",
      "DQS": "NONE",
      "TRUELVDS": true
    },
    {
      "INDEX": "261",
      "NAME": "IOR20B",
      "TYPE": "I/O",
      "BANK": 2,
      "DIFF": "N",
      "PAIR": "IOR20A",
      "DQS": "NONE"
    },
    {
      "INDEX": "262",
      "NAME": "IOR20A",
      "TYPE": "I/O",
      "BANK": 2,
      "DIFF": "P",
      "PAIR": "IOR20B",
      "DQS": "NONE"
    },
    {
      "INDEX": "263",
      "NAME": "IOR19B",
      "TYPE": "I/O",
      "BANK": 2,
      "DIFF": "N",
      "PAIR": "IOR19A",
      "DQS": "NONE",
      "TRUELVDS": true
    },
    {
      "INDEX": "264",
      "NAME": "IOR19A",
      "TYPE": "I/O",
      "BANK": 2,
      "DIFF": "P",
      "PAIR": "IOR19B",
      "DQS": "NONE",
      "TRUELVDS": true
    },
    {
      "INDEX": "265",
      "NAME": "IOR18B",
      "TYPE": "I/O",
      "BANK": 2,
      "DIFF": "N",
      "PAIR": "IOR18A",
      "DQS": "NONE"
    },
    {
      "INDEX": "266",
      "NAME": "IOR18A",
      "TYPE": "I/O",
      "BANK": 2,
      "DIFF": "P",
      "PAIR": "IOR18B",
      "DQS": "NONE"
    },
    {
      "INDEX": "267",
      "NAME": "IOR17B",
      "TYPE": "I/O",
      "BANK": 2,
      "DIFF": "N",
      "PAIR": "IOR17A",
      "DQS": "NONE",
      "TRUELVDS": true
    },
    {
      "INDEX": "268",
      "NAME": "IOR17A",
      "TYPE": "I/O",
      "BANK": 2,
      "DIFF": "P",
      "PAIR": "IOR17B",
      "DQS": "NONE",
      "TRUELVDS": true
    },
    {
      "INDEX": "269",
      "NAME": "IOR16B",
      "TYPE": "I/O",
      "BANK": 2,
      "DIFF": "N",
      "PAIR": "IOR16A",
      "DQS": "NONE"
    },
    {
      "INDEX": "270",
      "NAME": "IOR16A",
      "TYPE": "I/O",
      "BANK": 2,
      "DIFF": "P",
      "PAIR": "IOR16B",
      "DQS": "NONE"
    },
    {
      "INDEX": "271",
      "NAME": "IOR15B",
      "TYPE": "I/O",
      "BANK": 2,
      "DIFF": "N",
      "PAIR": "IOR15A",
      "DQS": "NONE",
      "TRUELVDS": true
    },
    {
      "INDEX": "272",
      "NAME": "IOR15A",
      "TYPE": "I/O",
      "BANK": 2,
      "DIFF": "P",
      "PAIR": "IOR15B",
      "DQS": "NONE",
      "TRUELVDS": true
    },
    {
      "INDEX": "273",
      "NAME": "IOR14B",
      "TYPE": "I/O",
      "BANK": 2,
      "DIFF": "N",
      "PAIR": "IOR14A",
      "DQS": "NONE"
    },
    {
      "INDEX": "274",
      "NAME": "IOR14A",
      "TYPE": "I/O",
      "BANK": 2,
      "DIFF": "P",
      "PAIR": "IOR14B",
      "DQS": "NONE"
    },
    {
      "INDEX": "275",
      "NAME": "IOR13B",
      "TYPE": "I/O",
      "BANK": 2,
      "DIFF": "N",
      "PAIR": "IOR13A",
      "DQS": "NONE",
      "TRUELVDS": true
    },
    {
      "INDEX": "276",
      "NAME": "IOR13A",
      "TYPE": "I/O",
      "BANK": 2,
      "DIFF": "P",
      "PAIR": "IOR13B",
      "DQS": "NONE",
      "TRUELVDS": true
    },
    {
      "INDEX": "277",
      "NAME": "IOR12B",
      "TYPE": "I/O",
      "BANK": 2,
      "DIFF": "N",
      "PAIR": "IOR12A",
      "DQS": "NONE"
    },
    {
      "INDEX": "278",
      "NAME": "IOR12A",
      "TYPE": "I/O",
      "BANK": 2,
      "DIFF": "P",
      "PAIR": "IOR12B",
      "DQS": "NONE"
    },
    {
      "INDEX": "279",
      "NAME": "IOR11B",
      "TYPE": "I/O",
      "BANK": 2,
      "DIFF": "N",
      "PAIR": "IOR11A",
      "DQS": "NONE",
      "TRUELVDS": true
    },
    {
      "INDEX": "280",
      "NAME": "IOR11A",
      "TYPE": "I/O",
      "BANK": 2,
      "DIFF": "P",
      "PAIR": "IOR11B",
      "DQS": "NONE",
      "TRUELVDS": true
    },
    {
      "INDEX": "281",
      "NAME": "IOR9B",
      "TYPE": "I/O",
      "BANK": 2,
      "DIFF": "N",
      "PAIR": "IOR9A",
      "DQS": "DQ5"
    },
    {
      "INDEX": "282",
      "NAME": "IOR9A",
      "TYPE": "I/O",
      "BANK": 2,
      "DIFF": "P",
      "PAIR": "IOR9B",
      "DQS": "DQ5"
    },
    {
      "INDEX": "283",
      "NAME": "IOR8B",
      "TYPE": "I/O",
      "BANK": 2,
      "DIFF": "N",
      "PAIR": "IOR8A",
      "DQS": "DQ5",
      "TRUELVDS": true
    },
    {
      "INDEX": "284",
      "NAME": "IOR8A",
      "TYPE": "I/O",
      "BANK": 2,
      "DIFF": "P",
      "PAIR": "IOR8B",
      "DQS": "DQ5",
      "TRUELVDS": true
    },
    {
      "INDEX": "285",
      "NAME": "IOR7B",
      "TYPE": "I/O",
      "BANK": 2,
      "DIFF": "N",
      "PAIR": "IOR7A",
      "DQS": "DQ5"
    },
    {
      "INDEX": "286",
      "NAME": "IOR7A",
      "TYPE": "I/O",
      "BANK": 2,
      "DIFF": "P",
      "PAIR": "IOR7B",
      "DQS": "DQ5"
    },
    {
      "INDEX": "287",
      "NAME": "IOR6B",
      "TYPE": "I/O",
      "BANK": 2,
      "DIFF": "N",
      "PAIR": "IOR6A",
      "DQS": "DQS5",
      "TRUELVDS": true
    },
    {
      "INDEX": "288",
      "NAME": "IOR6A",
      "TYPE": "I/O",
      "BANK": 2,
      "DIFF": "P",
      "PAIR": "IOR6B",
      "DQS": "DQS5",
      "TRUELVDS": true
    },
    {
      "INDEX": "289",
      "NAME": "IOR5B",
      "TYPE": "I/O",
      "BANK": 2,
      "DIFF": "N",
      "PAIR": "IOR5A",
      "DQS": "DQ5"
    },
    {
      "INDEX": "290",
      "NAME": "IOR5A",
      "TYPE": "I/O",
      "BANK": 2,
      "DIFF": "P",
      "PAIR": "IOR5B",
      "DQS": "DQ5"
    },
    {
      "INDEX": "291",
      "NAME": "IOR4B",
      "TYPE": "I/O",
      "BANK": 2,
      "CFG": "RPLL_C_IN",
      "DIFF": "N",
      "PAIR": "IOR4A",
      "DQS": "DQ5",
      "TRUELVDS": true
    },
    {
      "INDEX": "292",
      "NAME": "IOR4A",
      "TYPE": "I/O",
      "BANK": 2,
      "CFG": "RPLL_T_IN",
      "DIFF": "P",
      "PAIR": "IOR4B",
      "DQS": "DQ5",
      "TRUELVDS": true
    },
    {
      "INDEX": "293",
      "NAME": "IOR3B",
      "TYPE": "I/O",
      "BANK": 2,
      "DIFF": "N",
      "PAIR": "IOR3A",
      "DQS": "DQ5"
    },
    {
      "INDEX": "294",
      "NAME": "IOR3A",
      "TYPE": "I/O",
      "BANK": 2,
      "DIFF": "P",
      "PAIR": "IOR3B",
      "DQS": "DQ5"
    },
    {
      "INDEX": "295",
      "NAME": "IOR2B",
      "TYPE": "I/O",
      "BANK": 2,
      "CFG": "RPLL_C_FB",
      "DIFF": "N",
      "PAIR": "IOR2A",
      "DQS": "DQ5",
      "TRUELVDS": true
    },
    {
      "INDEX": "296",
      "NAME": "IOR2A",
      "TYPE": "I/O",
      "BANK": 2,
      "CFG": "RPLL_T_FB",
      "DIFF": "P",
      "PAIR": "IOR2B",
      "DQS": "DQ5",
      "TRUELVDS": true
    },
    {
      "INDEX": "297",
      "NAME": "IOT55B",
      "TYPE": "I/O",
      "BANK": 1,
      "CFG": "DONE",
      "DIFF": "N",
      "PAIR": "IOT55A",
      "DQS": "DQ6"
    },
    {
      "INDEX": "298",
      "NAME": "IOT55A",
      "TYPE": "I/O",
      "BANK": 1,
      "CFG": "READY",
      "DIFF": "P",
      "PAIR": "IOT55B",
      "DQS": "DQ6"
    },
    {
      "INDEX": "299",
      "NAME": "IOT54B",
      "TYPE": "I/O",
      "BANK": 1,
      "DIFF": "N",
      "PAIR": "IOT54A",
      "DQS": "DQ6",
      "TRUELVDS": true
    },
    {
      "INDEX": "300",
      "NAME": "IOT54A",
      "TYPE": "I/O",
      "BANK": 1,
      "DIFF": "P",
      "PAIR": "IOT54B",
      "DQS": "DQ6",
      "TRUELVDS": true
    },
    {
      "INDEX": "301",
      "NAME": "IOT53B",
      "TYPE": "I/O",
      "BANK": 1,
      "DIFF": "N",
      "PAIR": "IOT53A",
      "DQS": "DQ6"
    },
    {
      "INDEX": "302",
      "NAME": "IOT53A",
      "TYPE": "I/O",
      "BANK": 1,
      "DIFF": "P",
      "PAIR": "IOT53B",
      "DQS": "DQ6"
    },
    {
      "INDEX": "303",
      "NAME": "IOT52B",
      "TYPE": "I/O",
      "BANK": 1,
      "DIFF": "N",
      "PAIR": "IOT52A",
      "DQS": "DQ6",
      "TRUELVDS": true
    },
    {
      "INDEX": "304",
      "NAME": "IOT52A",
      "TYPE": "I/O",
      "BANK": 1,
      "DIFF": "P",
      "PAIR": "IOT52B",
      "DQS": "DQ6",
      "TRUELVDS": true
    },
    {
      "INDEX": "305",
      "NAME": "IOT51B",
      "TYPE": "I/O",
      "BANK": 1,
      "DIFF": "N",
      "PAIR": "IOT51A",
      "DQS": "DQ6"
    },
    {
      "INDEX": "306",
      "NAME": "IOT51A",
      "TYPE": "I/O",
      "BANK": 1,
      "DIFF": "P",
      "PAIR": "IOT51B",
      "DQS": "DQ6"
    },
    {
      "INDEX": "307",
      "NAME": "IOT50B",
      "TYPE": "I/O",
      "BANK": 1,
      "DIFF": "N",
      "PAIR": "IOT50A",
      "DQS": "DQ6",
      "TRUELVDS": true
    },
    {
      "INDEX": "308",
      "NAME": "IOT50A",
      "TYPE": "I/O",
      "BANK": 1,
      "DIFF": "P",
      "PAIR": "IOT50B",
      "DQS": "DQ6",
      "TRUELVDS": true
    },
    {
      "INDEX": "309",
      "NAME": "IOT49B",
      "TYPE": "I/O",
      "BANK": 1,
      "DIFF": "N",
      "PAIR": "IOT49A",
      "DQS": "DQ6"
    },
    {
      "INDEX": "310",
      "NAME": "IOT49A",
      "TYPE": "I/O",
      "BANK": 1,
      "DIFF": "P",
      "PAIR": "IOT49B",
      "DQS": "DQ6"
    },
    {
      "INDEX": "311",
      "NAME": "IOT48B",
      "TYPE": "I/O",
      "BANK": 1,
      "DIFF": "N",
      "PAIR": "IOT48A",
      "DQS": "DQS6",
      "TRUELVDS": true
    },
    {
      "INDEX": "312",
      "NAME": "IOT48A",
      "TYPE": "I/O",
      "BANK": 1,
      "DIFF": "P",
      "PAIR": "IOT48B",
      "DQS": "DQS6",
      "TRUELVDS": true
    },
    {
      "INDEX": "313",
      "NAME": "IOT45B",
      "TYPE": "I/O",
      "BANK": 1,
      "DIFF": "N",
      "PAIR": "IOT45A",
      "DQS": "DQ7"
    },
    {
      "INDEX": "314",
      "NAME": "IOT45A",
      "TYPE": "I/O",
      "BANK": 1,
      "DIFF": "P",
      "PAIR": "IOT45B",
      "DQS": "DQ7"
    },
    {
      "INDEX": "315",
      "NAME": "IOT44B",
      "TYPE": "I/O",
      "BANK": 1,
      "DIFF": "N",
      "PAIR": "IOT44A",
      "DQS": "DQ7",
      "TRUELVDS": true
    },
    {
      "INDEX": "316",
      "NAME": "IOT44A",
      "TYPE": "I/O",
      "BANK": 1,
      "DIFF": "P",
      "PAIR": "IOT44B",
      "DQS": "DQ7",
      "TRUELVDS": true
    },
    {
      "INDEX": "317",
      "NAME": "IOT43B",
      "TYPE": "I/O",
      "BANK": 1,
      "DIFF": "N",
      "PAIR": "IOT43A",
      "DQS": "DQ7"
    },
    {
      "INDEX": "318",
      "NAME": "IOT43A",
      "TYPE": "I/O",
      "BANK": 1,
      "DIFF": "P",
      "PAIR": "IOT43B",
      "DQS": "DQ7"
    },
    {
      "INDEX": "319",
      "NAME": "IOT42B",
      "TYPE": "I/O",
      "BANK": 1,
      "DIFF": "N",
      "PAIR": "IOT42A",
      "DQS": "DQ7",
      "TRUELVDS": true
    },
    {
      "INDEX": "320",
      "NAME": "IOT42A",
      "TYPE": "I/O",
      "BANK": 1,
      "DIFF": "P",
      "PAIR": "IOT42B",
      "DQS": "DQ7",
      "TRUELVDS": true
    },
    {
      "INDEX": "321",
      "NAME": "IOT41B",
      "TYPE": "I/O",
      "BANK": 1,
      "DIFF": "N",
      "PAIR": "IOT41A",
      "DQS": "DQ7"
    },
    {
      "INDEX": "322",
      "NAME": "IOT41A",
      "TYPE": "I/O",
      "BANK": 1,
      "DIFF": "P",
      "PAIR": "IOT41B",
      "DQS": "DQ7"
    },
    {
      "INDEX": "323",
      "NAME": "IOT40B",
      "TYPE": "I/O",
      "BANK": 1,
      "DIFF": "N",
      "PAIR": "IOT40A",
      "DQS": "DQ7",
      "TRUELVDS": true
    },
    {
      "INDEX": "324",
      "NAME": "IOT40A",
      "TYPE": "I/O",
      "BANK": 1,
      "DIFF": "P",
      "PAIR": "IOT40B",
      "DQS": "DQ7",
      "TRUELVDS": true
    },
    {
      "INDEX": "325",
      "NAME": "IOT39B",
      "TYPE": "I/O",
      "BANK": 1,
      "CFG": "RECONFIG_N",
      "DIFF": "N",
      "PAIR": "IOT39A",
      "DQS": "DQ7"
    },
    {
      "INDEX": "326",
      "NAME": "IOT39A",
      "TYPE": "I/O",
      "BANK": 1,
      "CFG": "JTAGSEL_N",
      "DIFF": "P",
      "PAIR": "IOT39B",
      "DQS": "DQ7"
    },
    {
      "INDEX": "327",
      "NAME": "IOT38B",
      "TYPE": "I/O",
      "BANK": 1,
      "DIFF": "N",
      "PAIR": "IOT38A",
      "DQS": "DQ7",
      "TRUELVDS": true
    },
    {
      "INDEX": "328",
      "NAME": "IOT38A",
      "TYPE": "I/O",
      "BANK": 1,
      "DIFF": "P",
      "PAIR": "IOT38B",
      "DQS": "DQ7",
      "TRUELVDS": true
    },
    {
      "INDEX": "329",
      "NAME": "IOT37B",
      "TYPE": "I/O",
      "BANK": 1,
      "DIFF": "N",
      "PAIR": "IOT37A",
      "DQS": "DQS7"
    },
    {
      "INDEX": "330",
      "NAME": "IOT37A",
      "TYPE": "I/O",
      "BANK": 1,
      "DIFF": "P",
      "PAIR": "IOT37B",
      "DQS": "DQS7"
    },
    {
      "INDEX": "331",
      "NAME": "IOT36B",
      "TYPE": "I/O",
      "BANK": 1,
      "DIFF": "N",
      "PAIR": "IOT36A",
      "DQS": "DQ7",
      "TRUELVDS": true
    },
    {
      "INDEX": "332",
      "NAME": "IOT36A",
      "TYPE": "I/O",
      "BANK": 1,
      "DIFF": "P",
      "PAIR": "IOT36B",
      "DQS": "DQ7",
      "TRUELVDS": true
    },
    {
      "INDEX": "333",
      "NAME": "IOT35B",
      "TYPE": "I/O",
      "BANK": 1,
      "DIFF": "N",
      "PAIR": "IOT35A",
      "DQS": "DQ7"
    },
    {
      "INDEX": "334",
      "NAME": "IOT35A",
      "TYPE": "I/O",
      "BANK": 1,
      "DIFF": "P",
      "PAIR": "IOT35B",
      "DQS": "DQ7"
    },
    {
      "INDEX": "335",
      "NAME": "IOT34B",
      "TYPE": "I/O",
      "BANK": 1,
      "DIFF": "N",
      "PAIR": "IOT34A",
      "DQS": "DQ7",
      "TRUELVDS": true
    },
    {
      "INDEX": "336",
      "NAME": "IOT34A",
      "TYPE": "I/O",
      "BANK": 1,
      "DIFF": "P",
      "PAIR": "IOT34B",
      "DQS": "DQ7",
      "TRUELVDS": true
    },
    {
      "INDEX": "337",
      "NAME": "IOT33B",
      "TYPE": "I/O",
      "BANK": 1,
      "DIFF": "N",
      "PAIR": "IOT33A",
      "DQS": "DQ7"
    },
    {
      "INDEX": "338",
      "NAME": "IOT33A",
      "TYPE": "I/O",
      "BANK": 1,
      "DIFF": "P",
      "PAIR": "IOT33B",
      "DQS": "DQ7"
    },
    {
      "INDEX": "339",
      "NAME": "IOT32B",
      "TYPE": "I/O",
      "BANK": 1,
      "DIFF": "N",
      "PAIR": "IOT32A",
      "DQS": "DQ7",
      "TRUELVDS": true
    },
    {
      "INDEX": "340",
      "NAME": "IOT32A",
      "TYPE": "I/O",
      "BANK": 1,
      "DIFF": "P",
      "PAIR": "IOT32B",
      "DQS": "DQ7",
      "TRUELVDS": true
    },
    {
      "INDEX": "341",
      "NAME": "IOT31B",
      "TYPE": "I/O",
      "BANK": 1,
      "CFG": "SDA/GCLKC_1",
      "DIFF": "N",
      "PAIR": "IOT31A",
      "DQS": "DQ7"
    },
    {
      "INDEX": "342",
      "NAME": "IOT31A",
      "TYPE": "I/O",
      "BANK": 1,
      "CFG": "SCL/GCLKT_1",
      "DIFF": "P",
      "PAIR": "IOT31B",
      "DQS": "DQ7"
    },
    {
      "INDEX": "343",
      "NAME": "IOT30B",
      "TYPE": "I/O",
      "BANK": 1,
      "DIFF": "N",
      "PAIR": "IOT30A",
      "DQS": "DQ7",
      "TRUELVDS": true
    },
    {
      "INDEX": "344",
      "NAME": "IOT30A",
      "TYPE": "I/O",
      "BANK": 1,
      "DIFF": "P",
      "PAIR": "IOT30B",
      "DQS": "DQ7",
      "TRUELVDS": true
    },
    {
      "INDEX": "345",
      "NAME": "IOT27B",
      "TYPE": "I/O",
      "BANK": 0,
      "DIFF": "N",
      "PAIR": "IOT27A",
      "DQS": "DQ8"
    },
    {
      "INDEX": "346",
      "NAME": "IOT27A",
      "TYPE": "I/O",
      "BANK": 0,
      "DIFF": "P",
      "PAIR": "IOT27B",
      "DQS": "DQ8"
    },
    {
      "INDEX": "347",
      "NAME": "IOT26B",
      "TYPE": "I/O",
      "BANK": 0,
      "DIFF": "N",
      "PAIR": "IOT26A",
      "DQS": "DQ8",
      "TRUELVDS": true
    },
    {
      "INDEX": "348",
      "NAME": "IOT26A",
      "TYPE": "I/O",
      "BANK": 0,
      "DIFF": "P",
      "PAIR": "IOT26B",
      "DQS": "DQ8",
      "TRUELVDS": true
    },
    {
      "INDEX": "349",
      "NAME": "IOT25B",
      "TYPE": "I/O",
      "BANK": 0,
      "DIFF": "N",
      "PAIR": "IOT25A",
      "DQS": "DQ8"
    },
    {
      "INDEX": "350",
      "NAME": "IOT25A",
      "TYPE": "I/O",
      "BANK": 0,
      "DIFF": "P",
      "PAIR": "IOT25B",
      "DQS": "DQ8"
    },
    {
      "INDEX": "351",
      "NAME": "IOT24B",
      "TYPE": "I/O",
      "BANK": 0,
      "CFG": "GCLKC_0",
      "DIFF": "N",
      "PAIR": "IOT24A",
      "DQS": "DQ8",
      "TRUELVDS": true
    },
    {
      "INDEX": "352",
      "NAME": "IOT24A",
      "TYPE": "I/O",
      "BANK": 0,
      "CFG": "GCLKT_0",
      "DIFF": "P",
      "PAIR": "IOT24B",
      "DQS": "DQ8",
      "TRUELVDS": true
    },
    {
      "INDEX": "353",
      "NAME": "IOT23B",
      "TYPE": "I/O",
      "BANK": 0,
      "CFG": "TMS",
      "DIFF": "N",
      "PAIR": "IOT23A",
      "DQS": "DQ8"
    },
    {
      "INDEX": "354",
      "NAME": "IOT23A",
      "TYPE": "I/O",
      "BANK": 0,
      "CFG": "TCK",
      "DIFF": "P",
      "PAIR": "IOT23B",
      "DQS": "DQ8"
    },
    {
      "INDEX": "355",
      "NAME": "IOT22B",
      "TYPE": "I/O",
      "BANK": 0,
      "DIFF": "N",
      "PAIR": "IOT22A",
      "DQS": "DQ8",
      "TRUELVDS": true
    },
    {
      "INDEX": "356",
      "NAME": "IOT22A",
      "TYPE": "I/O",
      "BANK": 0,
      "DIFF": "P",
      "PAIR": "IOT22B",
      "DQS": "DQ8",
      "TRUELVDS": true
    },
    {
      "INDEX": "357",
      "NAME": "IOT21B",
      "TYPE": "I/O",
      "BANK": 0,
      "DIFF": "N",
      "PAIR": "IOT21A",
      "DQS": "DQS8"
    },
    {
      "INDEX": "358",
      "NAME": "IOT21A",
      "TYPE": "I/O",
      "BANK": 0,
      "DIFF": "P",
      "PAIR": "IOT21B",
      "DQS": "DQS8"
    },
    {
      "INDEX": "359",
      "NAME": "IOT20B",
      "TYPE": "I/O",
      "BANK": 0,
      "DIFF": "N",
      "PAIR": "IOT20A",
      "DQS": "DQ8",
      "TRUELVDS": true
    },
    {
      "INDEX": "360",
      "NAME": "IOT20A",
      "TYPE": "I/O",
      "BANK": 0,
      "DIFF": "P",
      "PAIR": "IOT20B",
      "DQS": "DQ8",
      "TRUELVDS": true
    },
    {
      "INDEX": "361",
      "NAME": "IOT19B",
      "TYPE": "I/O",
      "BANK": 0,
      "DIFF": "N",
      "PAIR": "IOT19A",
      "DQS": "DQ8"
    },
    {
      "INDEX": "362",
      "NAME": "IOT19A",
      "TYPE": "I/O",
      "BANK": 0,
      "DIFF": "P",
      "PAIR": "IOT19B",
      "DQS": "DQ8"
    },
    {
      "INDEX": "363",
      "NAME": "IOT18B",
      "TYPE": "I/O",
      "BANK": 0,
      "DIFF": "N",
      "PAIR": "IOT18A",
      "DQS": "DQ8",
      "TRUELVDS": true
    },
    {
      "INDEX": "364",
      "NAME": "IOT18A",
      "TYPE": "I/O",
      "BANK": 0,
      "DIFF": "P",
      "PAIR": "IOT18B",
      "DQS": "DQ8",
      "TRUELVDS": true
    },
    {
      "INDEX": "365",
      "NAME": "IOT17B",
      "TYPE": "I/O",
      "BANK": 0,
      "CFG": "TDI",
      "DIFF": "N",
      "PAIR": "IOT17A",
      "DQS": "DQ8"
    },
    {
      "INDEX": "366",
      "NAME": "IOT17A",
      "TYPE": "I/O",
      "BANK": 0,
      "CFG": "TDO",
      "DIFF": "P",
      "PAIR": "IOT17B",
      "DQS": "DQ8"
    },
    {
      "INDEX": "367",
      "NAME": "IOT16B",
      "TYPE": "I/O",
      "BANK": 0,
      "DIFF": "N",
      "PAIR": "IOT16A",
      "DQS": "DQ8",
      "TRUELVDS": true
    },
    {
      "INDEX": "368",
      "NAME": "IOT16A",
      "TYPE": "I/O",
      "BANK": 0,
      "DIFF": "P",
      "PAIR": "IOT16B",
      "DQS": "DQ8",
      "TRUELVDS": true
    },
    {
      "INDEX": "369",
      "NAME": "IOT15B",
      "TYPE": "I/O",
      "BANK": 0,
      "DIFF": "N",
      "PAIR": "IOT15A",
      "DQS": "DQ8"
    },
    {
      "INDEX": "370",
      "NAME": "IOT15A",
      "TYPE": "I/O",
      "BANK": 0,
      "DIFF": "P",
      "PAIR": "IOT15B",
      "DQS": "DQ8"
    },
    {
      "INDEX": "371",
      "NAME": "IOT14B",
      "TYPE": "I/O",
      "BANK": 0,
      "DIFF": "N",
      "PAIR": "IOT14A",
      "DQS": "DQ8",
      "TRUELVDS": true
    },
    {
      "INDEX": "372",
      "NAME": "IOT14A",
      "TYPE": "I/O",
      "BANK": 0,
      "DIFF": "P",
      "PAIR": "IOT14B",
      "DQS": "DQ8",
      "TRUELVDS": true
    },
    {
      "INDEX": "373",
      "NAME": "IOT13B",
      "TYPE": "I/O",
      "BANK": 0,
      "DIFF": "N",
      "PAIR": "IOT13A",
      "DQS": "DQ8"
    },
    {
      "INDEX": "374",
      "NAME": "IOT13A",
      "TYPE": "I/O",
      "BANK": 0,
      "DIFF": "P",
      "PAIR": "IOT13B",
      "DQS": "DQ8"
    },
    {
      "INDEX": "375",
      "NAME": "IOT12B",
      "TYPE": "I/O",
      "BANK": 0,
      "DIFF": "N",
      "PAIR": "IOT12A",
      "DQS": "DQ8",
      "TRUELVDS": true
    },
    {
      "INDEX": "376",
      "NAME": "IOT12A",
      "TYPE": "I/O",
      "BANK": 0,
      "DIFF": "P",
      "PAIR": "IOT12B",
      "DQS": "DQ8",
      "TRUELVDS": true
    },
    {
      "INDEX": "377",
      "NAME": "IOT9B",
      "TYPE": "I/O",
      "BANK": 0,
      "DIFF": "N",
      "PAIR": "IOT9A",
      "DQS": "DQS9"
    },
    {
      "INDEX": "378",
      "NAME": "IOT9A",
      "TYPE": "I/O",
      "BANK": 0,
      "DIFF": "P",
      "PAIR": "IOT9B",
      "DQS": "DQS9"
    },
    {
      "INDEX": "379",
      "NAME": "IOT8B",
      "TYPE": "I/O",
      "BANK": 0,
      "DIFF": "N",
      "PAIR": "IOT8A",
      "DQS": "DQ9",
      "TRUELVDS": true
    },
    {
      "INDEX": "380",
      "NAME": "IOT8A",
      "TYPE": "I/O",
      "BANK": 0,
      "DIFF": "P",
      "PAIR": "IOT8B",
      "DQS": "DQ9",
      "TRUELVDS": true
    },
    {
      "INDEX": "381",
      "NAME": "IOT7B",
      "TYPE": "I/O",
      "BANK": 0,
      "DIFF": "N",
      "PAIR": "IOT7A",
      "DQS": "DQ9"
    },
    {
      "INDEX": "382",
      "NAME": "IOT7A",
      "TYPE": "I/O",
      "BANK": 0,
      "DIFF": "P",
      "PAIR": "IOT7B",
      "DQS": "DQ9"
    },
    {
      "INDEX": "383",
      "NAME": "IOT6B",
      "TYPE": "I/O",
      "BANK": 0,
      "DIFF": "N",
      "PAIR": "IOT6A",
      "DQS": "DQ9",
      "TRUELVDS": true
    },
    {
      "INDEX": "384",
      "NAME": "IOT6A",
      "TYPE": "I/O",
      "BANK": 0,
      "DIFF": "P",
      "PAIR": "IOT6B",
      "DQS": "DQ9",
      "TRUELVDS": true
    },
    {
      "INDEX": "385",
      "NAME": "IOT5B",
      "TYPE": "I/O",
      "BANK": 0,
      "DIFF": "N",
      "PAIR": "IOT5A",
      "DQS": "DQ9"
    },
    {
      "INDEX": "386",
      "NAME": "IOT5A",
      "TYPE": "I/O",
      "BANK": 0,
      "DIFF": "P",
      "PAIR": "IOT5B",
      "DQS": "DQ9"
    },
    {
      "INDEX": "387",
      "NAME": "IOT4B",
      "TYPE": "I/O",
      "BANK": 0,
      "DIFF": "N",
      "PAIR": "IOT4A",
      "DQS": "DQ9",
      "TRUELVDS": true
    },
    {
      "INDEX": "388",
      "NAME": "IOT4A",
      "TYPE": "I/O",
      "BANK": 0,
      "DIFF": "P",
      "PAIR": "IOT4B",
      "DQS": "DQ9",
      "TRUELVDS": true
    },
    {
      "INDEX": "389",
      "NAME": "IOT3B",
      "TYPE": "I/O",
      "BANK": 0,
      "DIFF": "N",
      "PAIR": "IOT3A",
      "DQS": "DQ9"
    },
    {
      "INDEX": "390",
      "NAME": "IOT3A",
      "TYPE": "I/O",
      "BANK": 0,
      "DIFF": "P",
      "PAIR": "IOT3B",
      "DQS": "DQ9"
    },
    {
      "INDEX": "391",
      "NAME": "IOT2B",
      "TYPE": "I/O",
      "BANK": 0,
      "DIFF": "N",
      "PAIR": "IOT2A",
      "DQS": "DQ9",
      "TRUELVDS": true
    },
    {
      "INDEX": "392",
      "NAME": "IOT2A",
      "TYPE": "I/O",
      "BANK": 0,
      "DIFF": "P",
      "PAIR": "IOT2B",
      "DQS": "DQ9",
      "TRUELVDS": true
    }
  ]
}